X30TianXuexi30ZhongxinJishuXilie/README.md
X30TianXuexi30ZhongxinJishuXilie/__init__.py
X30TianXuexi30ZhongxinJishuXilie/__main__.py
X30TianXuexi30ZhongxinJishuXilie/file.epub
X30TianXuexi30ZhongxinJishuXilie/index.html
X30TianXuexi30ZhongxinJishuXilie/css/__init__.py
X30TianXuexi30ZhongxinJishuXilie/css/annotations.css
X30TianXuexi30ZhongxinJishuXilie/css/main.css
X30TianXuexi30ZhongxinJishuXilie/css/normalize.css
X30TianXuexi30ZhongxinJishuXilie/css/popup.css
X30TianXuexi30ZhongxinJishuXilie/font/__init__.py
X30TianXuexi30ZhongxinJishuXilie/font/fontello.eot
X30TianXuexi30ZhongxinJishuXilie/font/fontello.svg
X30TianXuexi30ZhongxinJishuXilie/font/fontello.ttf
X30TianXuexi30ZhongxinJishuXilie/font/fontello.woff
X30TianXuexi30ZhongxinJishuXilie/img/__init__.py
X30TianXuexi30ZhongxinJishuXilie/img/annotator-glyph-sprite.png
X30TianXuexi30ZhongxinJishuXilie/img/annotator-icon-sprite.png
X30TianXuexi30ZhongxinJishuXilie/img/apple-touch-icon.png
X30TianXuexi30ZhongxinJishuXilie/img/cancelfullscreen.png
X30TianXuexi30ZhongxinJishuXilie/img/close.png
X30TianXuexi30ZhongxinJishuXilie/img/fullscreen.png
X30TianXuexi30ZhongxinJishuXilie/img/loader.gif
X30TianXuexi30ZhongxinJishuXilie/img/menu-icon.png
X30TianXuexi30ZhongxinJishuXilie/img/save.png
X30TianXuexi30ZhongxinJishuXilie/img/saved.png
X30TianXuexi30ZhongxinJishuXilie/img/settings-s.png
X30TianXuexi30ZhongxinJishuXilie/img/settings.png
X30TianXuexi30ZhongxinJishuXilie/img/star.png
X30TianXuexi30ZhongxinJishuXilie/js/__init__.py
X30TianXuexi30ZhongxinJishuXilie/js/epub.js
X30TianXuexi30ZhongxinJishuXilie/js/epub.min.js
X30TianXuexi30ZhongxinJishuXilie/js/epub.min.map
X30TianXuexi30ZhongxinJishuXilie/js/hooks.min.js
X30TianXuexi30ZhongxinJishuXilie/js/hooks.min.map
X30TianXuexi30ZhongxinJishuXilie/js/reader.js
X30TianXuexi30ZhongxinJishuXilie/js/reader.js.map
X30TianXuexi30ZhongxinJishuXilie/js/reader.min.js
X30TianXuexi30ZhongxinJishuXilie/js/reader.min.map
X30TianXuexi30ZhongxinJishuXilie/js/hooks/__init__.py
x30_tian_xuexi_30_zhongxin_jishu_xilie-2024.3.2.0.dist-info/METADATA
x30_tian_xuexi_30_zhongxin_jishu_xilie-2024.3.2.0.dist-info/WHEEL
x30_tian_xuexi_30_zhongxin_jishu_xilie-2024.3.2.0.dist-info/entry_points.txt
x30_tian_xuexi_30_zhongxin_jishu_xilie-2024.3.2.0.dist-info/top_level.txt
x30_tian_xuexi_30_zhongxin_jishu_xilie-2024.3.2.0.dist-info/RECORD
